groupdocs/__init__.py
groupdocs/comparison.cp310-win32.pyd
groupdocs/comparison.cp311-win32.pyd
groupdocs/comparison.cp35-win32.pyd
groupdocs/comparison.cp36-win32.pyd
groupdocs/comparison.cp37-win32.pyd
groupdocs/comparison.cp38-win32.pyd
groupdocs/comparison.cp39-win32.pyd
groupdocs/pycore.cp310-win32.pyd
groupdocs/pycore.cp311-win32.pyd
groupdocs/pycore.cp35-win32.pyd
groupdocs/pycore.cp36-win32.pyd
groupdocs/pycore.cp37-win32.pyd
groupdocs/pycore.cp38-win32.pyd
groupdocs/pycore.cp39-win32.pyd
groupdocs/pydrawing.cp310-win32.pyd
groupdocs/pydrawing.cp311-win32.pyd
groupdocs/pydrawing.cp35-win32.pyd
groupdocs/pydrawing.cp36-win32.pyd
groupdocs/pydrawing.cp37-win32.pyd
groupdocs/pydrawing.cp38-win32.pyd
groupdocs/pydrawing.cp39-win32.pyd
groupdocs/pygc.cp310-win32.pyd
groupdocs/pygc.cp311-win32.pyd
groupdocs/pygc.cp35-win32.pyd
groupdocs/pygc.cp36-win32.pyd
groupdocs/pygc.cp37-win32.pyd
groupdocs/pygc.cp38-win32.pyd
groupdocs/pygc.cp39-win32.pyd
groupdocs/pyreflection.cp310-win32.pyd
groupdocs/pyreflection.cp311-win32.pyd
groupdocs/pyreflection.cp35-win32.pyd
groupdocs/pyreflection.cp36-win32.pyd
groupdocs/pyreflection.cp37-win32.pyd
groupdocs/pyreflection.cp38-win32.pyd
groupdocs/pyreflection.cp39-win32.pyd
groupdocs/__pyinstaller/__init__.pyi
groupdocs/__pyinstaller/hook-groupdocs.py
groupdocs/assemblies/comparison/GroupDocs.Comparison.dll
groupdocs/assemblies/comparison/Microsoft.DotNet.PlatformAbstractions.dll
groupdocs/assemblies/comparison/Microsoft.Extensions.DependencyModel.dll
groupdocs/assemblies/comparison/Microsoft.Win32.SystemEvents.dll
groupdocs/assemblies/comparison/Newtonsoft.Json.dll
groupdocs/assemblies/comparison/SkiaSharp.dll
groupdocs/assemblies/comparison/System.Configuration.ConfigurationManager.dll
groupdocs/assemblies/comparison/System.Diagnostics.PerformanceCounter.dll
groupdocs/assemblies/comparison/System.Drawing.Common.dll
groupdocs/assemblies/comparison/System.Formats.Asn1.dll
GroupDocs.Comparison-24.6.dist-info/METADATA
GroupDocs.Comparison-24.6.dist-info/WHEEL
GroupDocs.Comparison-24.6.dist-info/entry_points.txt
GroupDocs.Comparison-24.6.dist-info/top_level.txt
GroupDocs.Comparison-24.6.dist-info/RECORD
