Metadata-Version: 2.1
Name: GroupDocs.Comparison
Version: 24.6
Summary: GroupDocs.Comparison for Python via .NET is a powerful API to compare over 50 types of documents and images, including all Microsoft Office and OpenDocument file formats, PDF documents, raster images (TIFF, JPEG, GIF, PNG, BMP). Retrieve the list of changes in the desired format with a line-by-line comparison of content, paragraphs, characters, styles, shapes, and position.
Home-page: https://products.groupdocs.com/comparison
Author: GroupDocs
License: Other/Proprietary License
Keywords: comparison,compare,file,api,pdf,docx,xlsx,pptx,html,png,word,excel,powerpoint,visio,opendocument,photoshop
Platform: win32
Classifier: Operating System :: Microsoft :: Windows
Classifier: Operating System :: POSIX :: Linux
Classifier: Operating System :: Unix
Classifier: License :: Other/Proprietary License
Classifier: Programming Language :: Python :: 3
Classifier: Programming Language :: Python :: 3 :: Only
Classifier: Programming Language :: Python :: 3.8
Classifier: Programming Language :: Python :: 3.9
Classifier: Topic :: Software Development :: Libraries
Classifier: Topic :: Utilities
Requires-Python: >=3.5,<3.12
